cfd_reader/__init__.py
cfd_reader/faces.py
cfd_reader/get_face.py
cfd_reader/preparation.py
cfd_reader-0.2.1.dist-info/METADATA
cfd_reader-0.2.1.dist-info/RECORD
cfd_reader-0.2.1.dist-info/WHEEL
cfd_reader-0.2.1.dist-info/top_level.txt
