Metadata-Version: 2.1
Name: cfd-reader
Version: 0.2.1
Summary: A Python module to access the Chicago Face Database
Home-page: http://gitlab.com/aalok-sathe/cfd-reader
Author: Aalok Sathe
Author-email: aalok.sathe@richmond.edu
License: GPL-3
Platform: UNKNOWN
Classifier: Development Status :: 1 - Planning
Classifier: Intended Audience :: Developers
Classifier: Intended Audience :: Education
Classifier: Intended Audience :: Science/Research
Classifier: License :: OSI Approved :: GNU General Public License v3 or later (GPLv3+)
Classifier: Programming Language :: Python :: 3.6
Classifier: Topic :: Software Development :: Libraries :: Python Modules
Requires-Python: >=3.5
Requires-Dist: numpy (>=1.13.0)
Requires-Dist: opencv-python (>=3.4.0.12)
Requires-Dist: progressbar2 (>=3.35.0)
Requires-Dist: xlrd (>=1.1.0)
